WoDeShuxuefenxiJimuXiudingban/README.md
WoDeShuxuefenxiJimuXiudingban/__init__.py
WoDeShuxuefenxiJimuXiudingban/__main__.py
WoDeShuxuefenxiJimuXiudingban/file.pdf
WoDeShuxuefenxiJimuXiudingban/index.html
wo_de_shuxuefenxi_jimu_xiudingban-2024.3.2.0.dist-info/METADATA
wo_de_shuxuefenxi_jimu_xiudingban-2024.3.2.0.dist-info/WHEEL
wo_de_shuxuefenxi_jimu_xiudingban-2024.3.2.0.dist-info/entry_points.txt
wo_de_shuxuefenxi_jimu_xiudingban-2024.3.2.0.dist-info/top_level.txt
wo_de_shuxuefenxi_jimu_xiudingban-2024.3.2.0.dist-info/RECORD
